locator/__init__.py
locator/api.py
locator/locator.py
locator-0.1.0.dist-info/LICENSE
locator-0.1.0.dist-info/WHEEL
locator-0.1.0.dist-info/METADATA
locator-0.1.0.dist-info/RECORD
