Metadata-Version: 2.1
Name: locator
Version: 0.1.0
Summary: 
Author: shidenggui
Author-email: 903618848@qq.com
Requires-Python: >=3.7,<4.0
Classifier: Programming Language :: Python :: 3
Classifier: Programming Language :: Python :: 3.7
Requires-Dist: lxml (>=4.4,<5.0)
